amundsen_common/__init__.py
amundsen_common/py.typed
amundsen_common/entity/__init__.py
amundsen_common/entity/resource_type.py
amundsen_common/log/__init__.py
amundsen_common/log/action_log.py
amundsen_common/log/action_log_callback.py
amundsen_common/log/action_log_model.py
amundsen_common/log/auth_caller_retrieval.py
amundsen_common/log/caller_retrieval.py
amundsen_common/log/http_header_caller_retrieval.py
amundsen_common/models/__init__.py
amundsen_common/models/badge.py
amundsen_common/models/dashboard.py
amundsen_common/models/feature.py
amundsen_common/models/generation_code.py
amundsen_common/models/index_map.py
amundsen_common/models/lineage.py
amundsen_common/models/popular_table.py
amundsen_common/models/search.py
amundsen_common/models/table.py
amundsen_common/models/tag.py
amundsen_common/models/user.py
amundsen_common/models/api/__init__.py
amundsen_common/models/api/health_check.py
amundsen_common/tests/__init__.py
amundsen_common/tests/fixtures.py
amundsen_common/utils/__init__.py
amundsen_common/utils/atlas.py
amundsen_common-0.32.0.dist-info/LICENSE
amundsen_common-0.32.0.dist-info/METADATA
amundsen_common-0.32.0.dist-info/NOTICE
amundsen_common-0.32.0.dist-info/WHEEL
amundsen_common-0.32.0.dist-info/top_level.txt
amundsen_common-0.32.0.dist-info/RECORD
