Metadata-Version: 2.1
Name: amundsen-common
Version: 0.32.0
Summary: Common code library for Amundsen
Home-page: https://github.com/amundsen-io/amundsen/tree/main/common
Maintainer: Amundsen TSC
Maintainer-email: amundsen-tsc@lists.lfai.foundation
License: UNKNOWN
Platform: UNKNOWN
Classifier: Programming Language :: Python :: 3.8
Classifier: Programming Language :: Python :: 3.9
Requires-Python: >=3.8
Requires-Dist: Flask >=2.2.5
Requires-Dist: attrs >=19.0.0
Requires-Dist: marshmallow >=3.0
Requires-Dist: marshmallow3-annotations >=1.1.0
Provides-Extra: all
Requires-Dist: flake8 >=3.9.2 ; extra == 'all'
Requires-Dist: flake8-tidy-imports >=4.3.0 ; extra == 'all'
Requires-Dist: isort[colors] ~=5.8.0 ; extra == 'all'
Requires-Dist: mock >=4.0.3 ; extra == 'all'
Requires-Dist: mypy <0.900,>=0.812 ; extra == 'all'
Requires-Dist: pytest >=6.2.4 ; extra == 'all'
Requires-Dist: pytest-cov >=2.12.0 ; extra == 'all'
Requires-Dist: pytest-env >=0.6.2 ; extra == 'all'
Requires-Dist: pytest-mock >=3.6.1 ; extra == 'all'
Requires-Dist: typed-ast >=1.4.3 ; extra == 'all'
Requires-Dist: pyspark ==3.0.1 ; extra == 'all'
